mitsuki/__init__.py
mitsuki/exceptions.py
mitsuki/cli/__init__.py
mitsuki/cli/bootstrap.py
mitsuki/cli/templates/README.md.tpl
mitsuki/cli/templates/__init__.py.tpl
mitsuki/cli/templates/alembic.ini.tpl
mitsuki/cli/templates/alembic_env.py.tpl
mitsuki/cli/templates/alembic_script.py.mako.tpl
mitsuki/cli/templates/app.py.tpl
mitsuki/cli/templates/application-dev.yml.tpl
mitsuki/cli/templates/application-prod.yml.tpl
mitsuki/cli/templates/application-stg.yml.tpl
mitsuki/cli/templates/application.yml.tpl
mitsuki/cli/templates/controller.py.tpl
mitsuki/cli/templates/entity.py.tpl
mitsuki/cli/templates/gitignore.tpl
mitsuki/cli/templates/repository.py.tpl
mitsuki/cli/templates/service.py.tpl
mitsuki/config/__init__.py
mitsuki/config/decorators.py
mitsuki/config/defaults.yml
mitsuki/config/exceptions.py
mitsuki/config/properties.py
mitsuki/core/__init__.py
mitsuki/core/application.py
mitsuki/core/container.py
mitsuki/core/decorators.py
mitsuki/core/enums.py
mitsuki/core/logging.py
mitsuki/core/metrics.py
mitsuki/core/providers.py
mitsuki/core/scanner.py
mitsuki/core/scheduler.py
mitsuki/core/server.py
mitsuki/core/utils.py
mitsuki/data/__init__.py
mitsuki/data/entity.py
mitsuki/data/query.py
mitsuki/data/query_decorators.py
mitsuki/data/query_parser.py
mitsuki/data/repository.py
mitsuki/data/types.py
mitsuki/data/adapters/__init__.py
mitsuki/data/adapters/base.py
mitsuki/data/adapters/sqlalchemy.py
mitsuki/openapi/__init__.py
mitsuki/openapi/decorators.py
mitsuki/openapi/generator.py
mitsuki/openapi/introspector.py
mitsuki/openapi/schemas.py
mitsuki/openapi/ui.py
mitsuki/web/__init__.py
mitsuki/web/controllers.py
mitsuki/web/mappings.py
mitsuki/web/multipart.py
mitsuki/web/parameter_binder.py
mitsuki/web/params.py
mitsuki/web/response.py
mitsuki/web/response_processor.py
mitsuki/web/route_builder.py
mitsuki/web/serialization.py
mitsuki/web/upload.py
mitsuki-0.1.4.dist-info/licenses/LICENSE.md
mitsuki-0.1.4.dist-info/METADATA
mitsuki-0.1.4.dist-info/WHEEL
mitsuki-0.1.4.dist-info/entry_points.txt
mitsuki-0.1.4.dist-info/top_level.txt
mitsuki-0.1.4.dist-info/RECORD
