Metadata-Version: 2.4
Name: mitsuki
Version: 0.1.4
Summary: Python web development framework. Mixing Python's productivity and flexibility with battle-hardened enterprise patterns.
Author: David Landup
License-Expression: Apache-2.0
Project-URL: Homepage, https://github.com/DavidLandup0/mitsuki
Project-URL: Documentation, https://github.com/DavidLandup0/mitsuki/blob/main/README.md
Project-URL: Repository, https://github.com/DavidLandup0/mitsuki
Project-URL: Issues, https://github.com/DavidLandup0/mitsuki/issues
Keywords: web,framework,python,asgi,dependency-injection
Classifier: Development Status :: 3 - Alpha
Classifier: Intended Audience :: Developers
Classifier: Programming Language :: Python :: 3
Classifier: Programming Language :: Python :: 3.9
Classifier: Programming Language :: Python :: 3.10
Classifier: Programming Language :: Python :: 3.11
Classifier: Programming Language :: Python :: 3.12
Classifier: Topic :: Internet :: WWW/HTTP
Classifier: Topic :: Software Development :: Libraries :: Application Frameworks
Requires-Python: >=3.9
License-File: LICENSE.md
Requires-Dist: uvicorn>=0.24.0
Requires-Dist: starlette>=0.32.0
Requires-Dist: sqlalchemy>=2.0.0
Requires-Dist: aiosqlite>=0.19.0
Requires-Dist: pyyaml>=6.0
Requires-Dist: click>=8.0.0
Requires-Dist: granian>=1.0.0
Requires-Dist: socketify>=0.0.27
Requires-Dist: python-multipart>=0.0.20
Requires-Dist: colorama>=0.4.6
Requires-Dist: croniter>=2.0.0
Requires-Dist: pytz>=2021.1
Requires-Dist: orjson>=3.9.0
Provides-Extra: postgresql
Requires-Dist: asyncpg>=0.29.0; extra == "postgresql"
Provides-Extra: dev
Requires-Dist: pytest>=7.4.0; extra == "dev"
Requires-Dist: pytest-asyncio>=0.21.0; extra == "dev"
Dynamic: license-file
